fast_controller-0.4.5b0.dist-info/METADATA
fast_controller-0.4.5b0.dist-info/WHEEL
fast_controller-0.4.5b0.dist-info/entry_points.txt
fast_controller/__init__.py
fast_controller/resource.py
fast_controller/schema.py
fast_controller/util.py
fast_controller-0.4.5b0.dist-info/RECORD
