Metadata-Version: 2.1
Name: Fast-Controller
Version: 0.4.5b0
Summary: The fastest way to a turn your models into a full ReST API
Keywords: controller,base,rest,api,backend
Author-Email: Cody M Sommer <bassmastacod@gmail.com>
License: MIT
Classifier: License :: OSI Approved :: MIT License
Classifier: Programming Language :: Python :: 3.7
Classifier: Programming Language :: Python :: 3.8
Classifier: Programming Language :: Python :: 3.9
Classifier: Programming Language :: Python :: 3.10
Classifier: Programming Language :: Python :: 3.11
Classifier: Programming Language :: Python :: 3.12
Classifier: Programming Language :: Python :: 3.13
Classifier: Programming Language :: Python :: 3.14
Classifier: Development Status :: 2 - Pre-Alpha
Classifier: Intended Audience :: Developers
Classifier: Topic :: Software Development :: Libraries
Classifier: Typing :: Typed
Project-URL: Repository, https://github.com/BassMastaCod/Fast-Controller.git
Project-URL: Issues, https://github.com/BassMastaCod/Fast-Controller/issues
Requires-Python: >=3.7
Requires-Dist: fastapi
Requires-Dist: daomodel
Requires-Dist: SQLModel
Requires-Dist: inflect
Requires-Dist: str-case-util
